resolve_hosts/__init__.py
resolve_hosts/cli.py
resolve_hosts/resolver.py
resolve_hosts/whois.py
resolve_hosts-0.3.2.dist-info/licenses/LICENSE
resolve_hosts-0.3.2.dist-info/METADATA
resolve_hosts-0.3.2.dist-info/WHEEL
resolve_hosts-0.3.2.dist-info/entry_points.txt
resolve_hosts-0.3.2.dist-info/top_level.txt
resolve_hosts-0.3.2.dist-info/RECORD
