Metadata-Version: 2.4
Name: resolve-hosts
Version: 0.3.2
Summary: Resolve list of DNS hostnames.
Author-email: Darren Spruell <phatbuckett@gmail.com>
Project-URL: Homepage, https://github.com/dspruell/resolve-hosts
Classifier: Programming Language :: Python :: 3
License-File: LICENSE
Requires-Dist: aslookup
Requires-Dist: dnspython
Requires-Dist: tabulate
Requires-Dist: ujson
Requires-Dist: whois-format
Dynamic: license-file
